fastapi_sqlalchemy_toolkit/__init__.py
fastapi_sqlalchemy_toolkit/filters.py
fastapi_sqlalchemy_toolkit/model_manager.py
fastapi_sqlalchemy_toolkit/ordering.py
fastapi_sqlalchemy_toolkit/utils.py
fastapi_sqlalchemy_toolkit-0.7.17.dist-info/METADATA
fastapi_sqlalchemy_toolkit-0.7.17.dist-info/WHEEL
fastapi_sqlalchemy_toolkit-0.7.17.dist-info/licenses/AUTHORS
fastapi_sqlalchemy_toolkit-0.7.17.dist-info/licenses/LICENSE
fastapi_sqlalchemy_toolkit-0.7.17.dist-info/RECORD
