Metadata-Version: 2.4
Name: fastapi_sqlalchemy_toolkit
Version: 0.7.17
Summary: FastAPI SQLAlchemy Toolkit
Project-URL: Homepage, https://github.com/e-kondr01/fastapi-sqlalchemy-toolkit
Author-email: Egor Kondrashov <e.kondr01@gmail.com>
License-File: AUTHORS
License-File: LICENSE
Classifier: Operating System :: OS Independent
Classifier: Programming Language :: Python :: 3
Requires-Python: >=3.11
Requires-Dist: fastapi-pagination>=0.12.12
Requires-Dist: fastapi>=0.100.0
Requires-Dist: pydantic>=2.0.0
Requires-Dist: sqlalchemy>=2.0.0
